0x_json_schemas-2.0.0-py3.7-nspkg.pth
zero_ex/json_schemas/__init__.py
zero_ex/json_schemas/py.typed
zero_ex/json_schemas/schemas/address_schema.json
zero_ex/json_schemas/schemas/asset_pairs_request_opts_schema.json
zero_ex/json_schemas/schemas/block_param_schema.json
zero_ex/json_schemas/schemas/block_range_schema.json
zero_ex/json_schemas/schemas/call_data_schema.json
zero_ex/json_schemas/schemas/ec_signature_parameter_schema.json
zero_ex/json_schemas/schemas/ec_signature_schema.json
zero_ex/json_schemas/schemas/eip712_typed_data_schema.json
zero_ex/json_schemas/schemas/hex_schema.json
zero_ex/json_schemas/schemas/index_filter_values_schema.json
zero_ex/json_schemas/schemas/js_number_schema.json
zero_ex/json_schemas/schemas/number_schema.json
zero_ex/json_schemas/schemas/order_cancel_schema.json
zero_ex/json_schemas/schemas/order_config_request_schema.json
zero_ex/json_schemas/schemas/order_fill_or_kill_requests_schema.json
zero_ex/json_schemas/schemas/order_fill_requests_schema.json
zero_ex/json_schemas/schemas/order_hash_schema.json
zero_ex/json_schemas/schemas/order_schema.json
zero_ex/json_schemas/schemas/order_watcher_web_socket_request_schema.json
zero_ex/json_schemas/schemas/order_watcher_web_socket_utf8_message_schema.json
zero_ex/json_schemas/schemas/orderbook_request_schema.json
zero_ex/json_schemas/schemas/orders_request_opts_schema.json
zero_ex/json_schemas/schemas/orders_schema.json
zero_ex/json_schemas/schemas/paged_request_opts_schema.json
zero_ex/json_schemas/schemas/paginated_collection_schema.json
zero_ex/json_schemas/schemas/relayer_api_asset_data_pairs_response_schema.json
zero_ex/json_schemas/schemas/relayer_api_asset_data_pairs_schema.json
zero_ex/json_schemas/schemas/relayer_api_asset_data_trade_info_schema.json
zero_ex/json_schemas/schemas/relayer_api_error_response_schema.json
zero_ex/json_schemas/schemas/relayer_api_fee_recipients_response_schema.json
zero_ex/json_schemas/schemas/relayer_api_order_config_payload_schema.json
0x_json_schemas-2.0.0.dist-info/METADATA
0x_json_schemas-2.0.0.dist-info/WHEEL
0x_json_schemas-2.0.0.dist-info/namespace_packages.txt
0x_json_schemas-2.0.0.dist-info/top_level.txt
0x_json_schemas-2.0.0.dist-info/RECORD
